NCD_KNN_Classifier/__init__.py
NCD_KNN_Classifier/classifier.py
NCD_KNN_Classifier/utils.py
ncd_knn_classifier-0.2.1.dist-info/licenses/LICENSE
ncd_knn_classifier-0.2.1.dist-info/METADATA
ncd_knn_classifier-0.2.1.dist-info/WHEEL
ncd_knn_classifier-0.2.1.dist-info/top_level.txt
ncd_knn_classifier-0.2.1.dist-info/RECORD
