Metadata-Version: 2.4
Name: NCD_KNN_Classifier
Version: 0.2.1
Summary: A kNN classifier based on NCD distance metric for text compression
Author-email: Javier Montaño <franjamonga@icloud.com>
Project-URL: Homepage, https://github.com/M-CORE-hub/NCD-KNN-Classifier
Project-URL: Bug Tracker, https://github.com/M-CORE-hub/NCD-KNN-Classifier/issues
Classifier: Programming Language :: Python :: 3
Classifier: License :: OSI Approved :: MIT License
Classifier: Operating System :: OS Independent
Requires-Python: >=3.11
License-File: LICENSE
Requires-Dist: numpy==2.2.4
Requires-Dist: scikit-learn==1.6.1
Requires-Dist: tqdm==4.67.1
Requires-Dist: datasets==3.4.1
Dynamic: license-file
